[
  {
    "t": "2026-07-13T11:00:00+00:00",
    "P": 2.35,
    "S": 0.00182,
    "hs_ft": 1.91,
    "tp_s": 14.285714
  },
  {
    "t": "2026-07-13T12:00:00+00:00",
    "P": 2.35,
    "S": 0.00182,
    "hs_ft": 1.89,
    "tp_s": 14.285714
  },
  {
    "t": "2026-07-13T13:00:00+00:00",
    "P": 2.44,
    "S": 0.00185,
    "hs_ft": 1.92,
    "tp_s": 14.285714
  },
  {
    "t": "2026-07-13T14:00:00+00:00",
    "P": 2.44,
    "S": 0.00185,
    "hs_ft": 1.94,
    "tp_s": 14.285714
  },
  {
    "t": "2026-07-13T15:00:00+00:00",
    "P": 2.52,
    "S": 0.00188,
    "hs_ft": 1.97,
    "tp_s": 14.285714
  },
  {
    "t": "2026-07-13T16:00:00+00:00",
    "P": 2.6,
    "S": 0.00192,
    "hs_ft": 2.0,
    "tp_s": 14.285714
  },
  {
    "t": "2026-07-13T17:00:00+00:00",
    "P": 2.69,
    "S": 0.00195,
    "hs_ft": 2.02,
    "tp_s": 14.285714
  },
  {
    "t": "2026-07-13T18:00:00+00:00",
    "P": 2.87,
    "S": 0.00201,
    "hs_ft": 2.08,
    "tp_s": 14.285714
  },
  {
    "t": "2026-07-13T19:00:00+00:00",
    "P": 2.85,
    "S": 0.00238,
    "hs_ft": 2.17,
    "tp_s": 13.333333
  },
  {
    "t": "2026-07-13T20:00:00+00:00",
    "P": 2.93,
    "S": 0.00242,
    "hs_ft": 2.21,
    "tp_s": 13.333333
  },
  {
    "t": "2026-07-13T21:00:00+00:00",
    "P": 2.93,
    "S": 0.00242,
    "hs_ft": 2.21,
    "tp_s": 13.333333
  }
]