[
  {
    "t": "2026-06-16T19:26:00+00:00",
    "P": 16.56,
    "S": 0.00208,
    "hs_ft": 4.27,
    "tp_s": 20.0
  },
  {
    "t": "2026-06-16T19:00:00+00:00",
    "P": 7.94,
    "S": 0.00144,
    "hs_ft": 2.95,
    "tp_s": 20.0
  },
  {
    "t": "2026-06-16T20:00:00+00:00",
    "P": 7.76,
    "S": 0.00143,
    "hs_ft": 2.92,
    "tp_s": 20.0
  },
  {
    "t": "2026-06-16T21:00:00+00:00",
    "P": 7.59,
    "S": 0.00141,
    "hs_ft": 2.88,
    "tp_s": 20.0
  },
  {
    "t": "2026-06-16T22:00:00+00:00",
    "P": 7.76,
    "S": 0.00143,
    "hs_ft": 2.92,
    "tp_s": 20.0
  },
  {
    "t": "2026-06-16T23:00:00+00:00",
    "P": 7.94,
    "S": 0.00144,
    "hs_ft": 2.94,
    "tp_s": 20.0
  },
  {
    "t": "2026-06-17T00:00:00+00:00",
    "P": 7.94,
    "S": 0.00144,
    "hs_ft": 2.95,
    "tp_s": 20.0
  },
  {
    "t": "2026-06-17T01:00:00+00:00",
    "P": 7.94,
    "S": 0.00144,
    "hs_ft": 2.96,
    "tp_s": 20.0
  },
  {
    "t": "2026-06-17T02:00:00+00:00",
    "P": 8.12,
    "S": 0.00146,
    "hs_ft": 2.99,
    "tp_s": 20.0
  },
  {
    "t": "2026-06-17T02:56:00+00:00",
    "P": 11.86,
    "S": 0.00176,
    "hs_ft": 3.61,
    "tp_s": 20.0
  },
  {
    "t": "2026-06-17T02:00:00+00:00",
    "P": 8.12,
    "S": 0.00146,
    "hs_ft": 2.99,
    "tp_s": 20.0
  },
  {
    "t": "2026-06-17T03:00:00+00:00",
    "P": 8.48,
    "S": 0.00149,
    "hs_ft": 3.05,
    "tp_s": 20.0
  },
  {
    "t": "2026-06-17T04:00:00+00:00",
    "P": 8.84,
    "S": 0.00152,
    "hs_ft": 3.11,
    "tp_s": 20.0
  }
]