{
  "updated": "2026-07-11T03:45:37.349293+00:00",
  "station": {
    "name": "Bluff House Station Cayucos",
    "id": "219965",
    "tz": "America/Los_Angeles",
    "lat": 35.44921,
    "lon": -120.91595
  },
  "time": "2026-07-11T03:44:36+00:00",
  "air_f": 56,
  "feels_f": 56,
  "dew_f": 53,
  "humidity": 88,
  "wind_mph": 4,
  "gust_mph": 6,
  "lull_mph": 2,
  "wind_dir": 122,
  "pressure_mb": 978.8,
  "pressure_trend": "falling",
  "uv": 0.0,
  "solar_wm2": 0,
  "rain_in_today": 0.0,
  "lightning_count": 0,
  "lightning_mi": null
}