{
  "updated": "2026-07-23T18:20:26.730467+00:00",
  "station": {
    "name": "Bluff House Station Cayucos",
    "id": "219965",
    "tz": "America/Los_Angeles",
    "lat": 35.44921,
    "lon": -120.91595
  },
  "time": "2026-07-23T18:20:07+00:00",
  "air_f": 67,
  "feels_f": 67,
  "dew_f": 59,
  "humidity": 77,
  "wind_mph": 9,
  "gust_mph": 14,
  "lull_mph": 2,
  "wind_dir": 260,
  "pressure_mb": 1018.9,
  "pressure_trend": "rising",
  "uv": 9.42,
  "solar_wm2": 890,
  "rain_in_today": 0.0,
  "lightning_count": 0,
  "lightning_mi": null
}