{
  "updated": "2026-07-22T00:50:23.385764+00:00",
  "station": {
    "name": "Bluff House Station Cayucos",
    "id": "219965",
    "tz": "America/Los_Angeles",
    "lat": 35.44921,
    "lon": -120.91595
  },
  "time": "2026-07-22T00:49:44+00:00",
  "air_f": 72,
  "feels_f": 72,
  "dew_f": 59,
  "humidity": 65,
  "wind_mph": 5,
  "gust_mph": 7,
  "lull_mph": 2,
  "wind_dir": 248,
  "pressure_mb": 1001.6,
  "pressure_trend": "falling",
  "uv": 2.72,
  "solar_wm2": 255,
  "rain_in_today": 0.0,
  "lightning_count": 0,
  "lightning_mi": null
}