{
  "updated": "2026-06-06T17:48:01.561530+00:00",
  "station": {
    "name": "Bluff House Station Cayucos",
    "id": "219965",
    "tz": "America/Los_Angeles",
    "lat": 35.44921,
    "lon": -120.91595
  },
  "time": "2026-06-06T17:47:45+00:00",
  "air_f": 56,
  "feels_f": 56,
  "dew_f": 52,
  "humidity": 87,
  "wind_mph": 5,
  "gust_mph": 6,
  "lull_mph": 4,
  "wind_dir": 225,
  "pressure_mb": 1009.1,
  "pressure_trend": "rising",
  "uv": 10.82,
  "solar_wm2": 861,
  "rain_in_today": 0.0,
  "lightning_count": 0,
  "lightning_mi": null
}