{
  "updated": "2026-07-01T11:30:27.124659+00:00",
  "station": {
    "name": "Bluff House Station Cayucos",
    "id": "219965",
    "tz": "America/Los_Angeles",
    "lat": 35.44921,
    "lon": -120.91595
  },
  "time": "2026-07-01T11:30:03+00:00",
  "air_f": 55,
  "feels_f": 55,
  "dew_f": 51,
  "humidity": 86,
  "wind_mph": 2,
  "gust_mph": 3,
  "lull_mph": 1,
  "wind_dir": 239,
  "pressure_mb": 988.9,
  "pressure_trend": "rising",
  "uv": 0.0,
  "solar_wm2": 0,
  "rain_in_today": 0.0,
  "lightning_count": 0,
  "lightning_mi": null
}