{
  "updated": "2026-06-09T20:30:23.429897+00:00",
  "station": {
    "name": "Bluff House Station Cayucos",
    "id": "219965",
    "tz": "America/Los_Angeles",
    "lat": 35.44921,
    "lon": -120.91595
  },
  "time": "2026-06-09T20:29:40+00:00",
  "air_f": 71,
  "feels_f": 71,
  "dew_f": 57,
  "humidity": 60,
  "wind_mph": 6,
  "gust_mph": 10,
  "lull_mph": 2,
  "wind_dir": 308,
  "pressure_mb": 1021.0,
  "pressure_trend": "rising",
  "uv": 9.19,
  "solar_wm2": 1000,
  "rain_in_today": 0.0,
  "lightning_count": 0,
  "lightning_mi": null
}