{
  "updated": "2026-07-08T20:05:20.481532+00:00",
  "station": {
    "name": "Bluff House Station Cayucos",
    "id": "219965",
    "tz": "America/Los_Angeles",
    "lat": 35.44921,
    "lon": -120.91595
  },
  "time": "2026-07-08T20:04:26+00:00",
  "air_f": 65,
  "feels_f": 65,
  "dew_f": 56,
  "humidity": 71,
  "wind_mph": 10,
  "gust_mph": 17,
  "lull_mph": 4,
  "wind_dir": 281,
  "pressure_mb": 1018.2,
  "pressure_trend": "rising",
  "uv": 10.03,
  "solar_wm2": 992,
  "rain_in_today": 0.0,
  "lightning_count": 0,
  "lightning_mi": null
}