{
  "updated": "2026-07-13T19:20:12.274940+00:00",
  "station": {
    "name": "Bluff House Station Cayucos",
    "id": "219965",
    "tz": "America/Los_Angeles",
    "lat": 35.44921,
    "lon": -120.91595
  },
  "time": "2026-07-13T19:19:40+00:00",
  "air_f": 65,
  "feels_f": 65,
  "dew_f": 59,
  "humidity": 80,
  "wind_mph": 7,
  "gust_mph": 8,
  "lull_mph": 6,
  "wind_dir": 239,
  "pressure_mb": 1016.6,
  "pressure_trend": "rising",
  "uv": 7.38,
  "solar_wm2": 689,
  "rain_in_today": 0.0,
  "lightning_count": 0,
  "lightning_mi": null
}