{
  "updated": "2026-06-26T13:40:26.858457+00:00",
  "station": {
    "name": "Bluff House Station Cayucos",
    "id": "219965",
    "tz": "America/Los_Angeles",
    "lat": 35.44921,
    "lon": -120.91595
  },
  "time": "2026-06-26T13:39:47+00:00",
  "air_f": 57,
  "feels_f": 57,
  "dew_f": 53,
  "humidity": 85,
  "wind_mph": 3,
  "gust_mph": 3,
  "lull_mph": 2,
  "wind_dir": 174,
  "pressure_mb": 991.2,
  "pressure_trend": "steady",
  "uv": 0.17,
  "solar_wm2": 17,
  "rain_in_today": 0.0,
  "lightning_count": 0,
  "lightning_mi": null
}