{
  "updated": "2026-07-02T18:20:41.460394+00:00",
  "station": {
    "name": "Bluff House Station Cayucos",
    "id": "219965",
    "tz": "America/Los_Angeles",
    "lat": 35.44921,
    "lon": -120.91595
  },
  "time": "2026-07-02T18:20:36+00:00",
  "air_f": 59,
  "feels_f": 59,
  "dew_f": 51,
  "humidity": 77,
  "wind_mph": 8,
  "gust_mph": 10,
  "lull_mph": 5,
  "wind_dir": 247,
  "pressure_mb": 1014.0,
  "pressure_trend": "rising",
  "uv": 9.0,
  "solar_wm2": 895,
  "rain_in_today": 0.0,
  "lightning_count": 0,
  "lightning_mi": null
}