{
  "updated": "2026-07-07T16:35:14.155657+00:00",
  "station": {
    "name": "Bluff House Station Cayucos",
    "id": "219965",
    "tz": "America/Los_Angeles",
    "lat": 35.44921,
    "lon": -120.91595
  },
  "time": "2026-07-07T16:34:50+00:00",
  "air_f": 60,
  "feels_f": 60,
  "dew_f": 54,
  "humidity": 79,
  "wind_mph": 9,
  "gust_mph": 14,
  "lull_mph": 4,
  "wind_dir": 279,
  "pressure_mb": 1008.3,
  "pressure_trend": "rising",
  "uv": 6.35,
  "solar_wm2": 633,
  "rain_in_today": 0.0,
  "lightning_count": 0,
  "lightning_mi": null
}