{
  "updated": "2026-06-29T00:25:24.795797+00:00",
  "station": {
    "name": "Bluff House Station Cayucos",
    "id": "219965",
    "tz": "America/Los_Angeles",
    "lat": 35.44921,
    "lon": -120.91595
  },
  "time": "2026-06-29T00:24:55+00:00",
  "air_f": 65,
  "feels_f": 65,
  "dew_f": 55,
  "humidity": 69,
  "wind_mph": 7,
  "gust_mph": 13,
  "lull_mph": 2,
  "wind_dir": 287,
  "pressure_mb": 998.0,
  "pressure_trend": "falling",
  "uv": 3.71,
  "solar_wm2": 361,
  "rain_in_today": 0.0,
  "lightning_count": 0,
  "lightning_mi": null
}