{
  "updated": "2026-06-27T21:15:26.365850+00:00",
  "station": {
    "name": "Bluff House Station Cayucos",
    "id": "219965",
    "tz": "America/Los_Angeles",
    "lat": 35.44921,
    "lon": -120.91595
  },
  "time": "2026-06-27T21:15:19+00:00",
  "air_f": 70,
  "feels_f": 70,
  "dew_f": 57,
  "humidity": 63,
  "wind_mph": 11,
  "gust_mph": 16,
  "lull_mph": 5,
  "wind_dir": 294,
  "pressure_mb": 1017.3,
  "pressure_trend": "falling",
  "uv": 9.77,
  "solar_wm2": 952,
  "rain_in_today": 0.0,
  "lightning_count": 0,
  "lightning_mi": null
}