{
  "updated": "2026-07-04T01:40:26.159935+00:00",
  "station": {
    "name": "Bluff House Station Cayucos",
    "id": "219965",
    "tz": "America/Los_Angeles",
    "lat": 35.44921,
    "lon": -120.91595
  },
  "time": "2026-07-04T01:40:08+00:00",
  "air_f": 61,
  "feels_f": 61,
  "dew_f": 56,
  "humidity": 82,
  "wind_mph": 4,
  "gust_mph": 7,
  "lull_mph": 2,
  "wind_dir": 271,
  "pressure_mb": 994.0,
  "pressure_trend": "falling",
  "uv": 2.16,
  "solar_wm2": 217,
  "rain_in_today": 0.0,
  "lightning_count": 0,
  "lightning_mi": null
}