{
  "updated": "2026-07-01T01:50:27.013929+00:00",
  "station": {
    "name": "Bluff House Station Cayucos",
    "id": "219965",
    "tz": "America/Los_Angeles",
    "lat": 35.44921,
    "lon": -120.91595
  },
  "time": "2026-07-01T01:50:11+00:00",
  "air_f": 62,
  "feels_f": 62,
  "dew_f": 54,
  "humidity": 77,
  "wind_mph": 9,
  "gust_mph": 15,
  "lull_mph": 3,
  "wind_dir": 300,
  "pressure_mb": 992.4,
  "pressure_trend": "falling",
  "uv": 1.88,
  "solar_wm2": 184,
  "rain_in_today": 0.0,
  "lightning_count": 0,
  "lightning_mi": null
}